asesurfacefinder/__init__.py
asesurfacefinder/asesf.py
asesurfacefinder/exception.py
asesurfacefinder/plot.py
asesurfacefinder/sample_bounds.py
asesurfacefinder/utils.py
asesurfacefinder-1.1.0.dist-info/licenses/LICENSE
asesurfacefinder-1.1.0.dist-info/METADATA
asesurfacefinder-1.1.0.dist-info/WHEEL
asesurfacefinder-1.1.0.dist-info/top_level.txt
asesurfacefinder-1.1.0.dist-info/RECORD
