Metadata-Version: 2.4
Name: asesurfacefinder
Version: 1.1.0
Summary: Machine learned location of chemical adsorbates on high-symmetry surface sites.
Author-email: Joe Gilkes <joe@joegilk.es>
License: MIT License
Project-URL: Homepage, https://github.com/joegilkes/ASESurfaceFinder
Keywords: ase,surface,atoms,molecule,chemistry,adsorbate,random forest,classification
Classifier: License :: OSI Approved :: MIT License
Classifier: Programming Language :: Python
Classifier: Programming Language :: Python :: 3
Classifier: Programming Language :: Python :: 3.9
Classifier: Programming Language :: Python :: 3.10
Classifier: Programming Language :: Python :: 3.11
Classifier: Programming Language :: Python :: 3.12
Classifier: Programming Language :: Python :: 3.13
Classifier: Intended Audience :: Science/Research
Classifier: Operating System :: MacOS
Classifier: Operating System :: Unix
Requires-Python: >=3.9
License-File: LICENSE
Requires-Dist: numpy
Requires-Dist: scipy
Requires-Dist: scikit-learn
Requires-Dist: dscribe
Requires-Dist: ase
Requires-Dist: matplotlib
Dynamic: license-file
